examples/ICMS_2024.py
examples/MoRN_2025.py
examples/__init__.py
sign_vector_conditions/__init__.py
sign_vector_conditions/reaction_networks.py
sign_vector_conditions/robustness.py
sign_vector_conditions/unique_existence.py
sign_vector_conditions/uniqueness.py
sign_vector_conditions/utility.py
sign_vector_conditions-2.2.dist-info/licenses/LICENSE
sign_vector_conditions-2.2.dist-info/METADATA
sign_vector_conditions-2.2.dist-info/WHEEL
sign_vector_conditions-2.2.dist-info/top_level.txt
sign_vector_conditions-2.2.dist-info/RECORD
